[{"key":"fr","value":"1gAlaAxLoxkxchmmb.AWWcs1VdLe68Bi8RLQRyGEgxp9Y.BbzYju.jK.AAA.0.0.BbzYjv.AWULdpVg","expires":"2019-01-20T08:23:11.000Z","maxAge":7775998,"domain":"facebook.com","path":"/","secure":true,"httpOnly":true,"hostOnly":false,"creation":"2018-10-22T08:23:11.422Z","lastAccessed":"2018-10-22T08:23:17.234Z"},{"key":"sb","value":"7ojNW2rMxFCnZqAHt05saAst","expires":"2020-10-21T08:23:11.000Z","maxAge":63071998,"domain":"facebook.com","path":"/","secure":true,"httpOnly":true,"hostOnly":false,"creation":"2018-10-22T08:23:11.422Z","lastAccessed":"2018-10-22T08:23:17.234Z"},{"key":"datr","value":"7ojNW8AMtfrHIKGgcMYxsRPR","domain":"facebook.com","path":"/","hostOnly":false,"creation":"2018-10-22T08:23:11.515Z","lastAccessed":"2018-10-22T08:23:17.234Z"},{"key":"c_user","value":"100027295904383","expires":"2019-01-20T08:23:11.000Z","maxAge":7775998,"domain":"facebook.com","path":"/","secure":true,"hostOnly":false,"creation":"2018-10-22T08:23:13.078Z","lastAccessed":"2018-10-22T08:23:17.234Z"},{"key":"xs","value":"12%3ALRb38AZtwgIjYQ%3A2%3A1540196592%3A2162%3A10174","expires":"2019-01-20T08:23:11.000Z","maxAge":7775998,"domain":"facebook.com","path":"/","secure":true,"httpOnly":true,"hostOnly":false,"creation":"2018-10-22T08:23:13.078Z","lastAccessed":"2018-10-22T08:23:17.234Z"},{"key":"pl","value":"n","expires":"2019-01-20T08:23:11.000Z","maxAge":7775998,"domain":"facebook.com","path":"/","secure":true,"httpOnly":true,"hostOnly":false,"creation":"2018-10-22T08:23:13.078Z","lastAccessed":"2018-10-22T08:23:17.234Z"},{"key":"spin","value":"r.4445957_b.trunk_t.1540196593_s.1_v.2_","expires":"2018-10-23T09:23:13.000Z","maxAge":90000,"domain":"facebook.com","path":"/","secure":true,"httpOnly":true,"hostOnly":false,"creation":"2018-10-22T08:23:13.265Z","lastAccessed":"2018-10-22T08:23:17.234Z"},{"key":"presence","value":"EDvF3EtimeF1540196597EuserFA21B27295904383A2EstateFDutF0Et2F_5b_5dElm2FnullEuct2F1540196597047EtrFnullEtwF3725802356EatF1540196597047CEchFDp_5f1B27295904383F0CC","domain":"facebook.com","path":"/","secure":true,"hostOnly":false,"creation":"2018-10-22T08:23:17.047Z","lastAccessed":"2018-10-22T08:23:17.234Z"},{"key":"locale","value":"en_US","domain":"facebook.com","path":"/","secure":true,"hostOnly":false,"creation":"2018-10-22T08:23:17.047Z","lastAccessed":"2018-10-22T08:23:17.234Z"},{"key":"a11y","value":"%7B%22sr%22%3A0%2C%22sr-ts%22%3A1540196597047%2C%22jk%22%3A0%2C%22jk-ts%22%3A1540196597047%2C%22kb%22%3A0%2C%22kb-ts%22%3A1540196597047%2C%22hcm%22%3A0%2C%22hcm-ts%22%3A1540196597047%7D","domain":"facebook.com","path":"/","secure":true,"hostOnly":false,"creation":"2018-10-22T08:23:17.047Z","lastAccessed":"2018-10-22T08:23:17.234Z"},{"key":"fr","value":"1gAlaAxLoxkxchmmb.AWWcs1VdLe68Bi8RLQRyGEgxp9Y.BbzYju.jK.AAA.0.0.BbzYjv.AWULdpVg","expires":"2019-01-20T08:23:11.000Z","maxAge":7775998,"domain":"facebook.com","path":"/","secure":true,"httpOnly":true,"hostOnly":false,"creation":"2018-10-22T08:23:11.422Z","lastAccessed":"2018-10-22T08:23:17.234Z"},{"key":"sb","value":"7ojNW2rMxFCnZqAHt05saAst","expires":"2020-10-21T08:23:11.000Z","maxAge":63071998,"domain":"facebook.com","path":"/","secure":true,"httpOnly":true,"hostOnly":false,"creation":"2018-10-22T08:23:11.422Z","lastAccessed":"2018-10-22T08:23:17.234Z"},{"key":"datr","value":"7ojNW8AMtfrHIKGgcMYxsRPR","domain":"facebook.com","path":"/","hostOnly":false,"creation":"2018-10-22T08:23:11.515Z","lastAccessed":"2018-10-22T08:23:17.234Z"},{"key":"c_user","value":"100027295904383","expires":"2019-01-20T08:23:11.000Z","maxAge":7775998,"domain":"facebook.com","path":"/","secure":true,"hostOnly":false,"creation":"2018-10-22T08:23:13.078Z","lastAccessed":"2018-10-22T08:23:17.234Z"},{"key":"xs","value":"12%3ALRb38AZtwgIjYQ%3A2%3A1540196592%3A2162%3A10174","expires":"2019-01-20T08:23:11.000Z","maxAge":7775998,"domain":"facebook.com","path":"/","secure":true,"httpOnly":true,"hostOnly":false,"creation":"2018-10-22T08:23:13.078Z","lastAccessed":"2018-10-22T08:23:17.234Z"},{"key":"pl","value":"n","expires":"2019-01-20T08:23:11.000Z","maxAge":7775998,"domain":"facebook.com","path":"/","secure":true,"httpOnly":true,"hostOnly":false,"creation":"2018-10-22T08:23:13.078Z","lastAccessed":"2018-10-22T08:23:17.234Z"},{"key":"spin","value":"r.4445957_b.trunk_t.1540196593_s.1_v.2_","expires":"2018-10-23T09:23:13.000Z","maxAge":90000,"domain":"facebook.com","path":"/","secure":true,"httpOnly":true,"hostOnly":false,"creation":"2018-10-22T08:23:13.265Z","lastAccessed":"2018-10-22T08:23:17.234Z"},{"key":"presence","value":"EDvF3EtimeF1540196597EuserFA21B27295904383A2EstateFDutF0Et2F_5b_5dElm2FnullEuct2F1540196597047EtrFnullEtwF3725802356EatF1540196597047CEchFDp_5f1B27295904383F0CC","domain":"facebook.com","path":"/","secure":true,"hostOnly":false,"creation":"2018-10-22T08:23:17.047Z","lastAccessed":"2018-10-22T08:23:17.234Z"},{"key":"locale","value":"en_US","domain":"facebook.com","path":"/","secure":true,"hostOnly":false,"creation":"2018-10-22T08:23:17.047Z","lastAccessed":"2018-10-22T08:23:17.234Z"},{"key":"a11y","value":"%7B%22sr%22%3A0%2C%22sr-ts%22%3A1540196597047%2C%22jk%22%3A0%2C%22jk-ts%22%3A1540196597047%2C%22kb%22%3A0%2C%22kb-ts%22%3A1540196597047%2C%22hcm%22%3A0%2C%22hcm-ts%22%3A1540196597047%7D","domain":"facebook.com","path":"/","secure":true,"hostOnly":false,"creation":"2018-10-22T08:23:17.047Z","lastAccessed":"2018-10-22T08:23:17.234Z"},{"key":"fr","value":"1gAlaAxLoxkxchmmb.AWWcs1VdLe68Bi8RLQRyGEgxp9Y.BbzYju.jK.AAA.0.0.BbzYjv.AWULdpVg","expires":"2019-01-20T08:23:11.000Z","maxAge":7775998,"domain":"messenger.com","path":"/","secure":true,"httpOnly":true,"hostOnly":false,"creation":"2018-10-22T08:23:11.422Z","lastAccessed":"2018-10-22T08:23:17.234Z"},{"key":"sb","value":"7ojNW2rMxFCnZqAHt05saAst","expires":"2020-10-21T08:23:11.000Z","maxAge":63071998,"domain":"messenger.com","path":"/","secure":true,"httpOnly":true,"hostOnly":false,"creation":"2018-10-22T08:23:11.422Z","lastAccessed":"2018-10-22T08:23:17.234Z"},{"key":"c_user","value":"100027295904383","expires":"2019-01-20T08:23:11.000Z","maxAge":7775998,"domain":"messenger.com","path":"/","secure":true,"hostOnly":false,"creation":"2018-10-22T08:23:13.078Z","lastAccessed":"2018-10-22T08:23:17.234Z"},{"key":"xs","value":"12%3ALRb38AZtwgIjYQ%3A2%3A1540196592%3A2162%3A10174","expires":"2019-01-20T08:23:11.000Z","maxAge":7775998,"domain":"messenger.com","path":"/","secure":true,"httpOnly":true,"hostOnly":false,"creation":"2018-10-22T08:23:13.078Z","lastAccessed":"2018-10-22T08:23:17.234Z"},{"key":"pl","value":"n","expires":"2019-01-20T08:23:11.000Z","maxAge":7775998,"domain":"messenger.com","path":"/","secure":true,"httpOnly":true,"hostOnly":false,"creation":"2018-10-22T08:23:13.078Z","lastAccessed":"2018-10-22T08:23:17.234Z"},{"key":"spin","value":"r.4445957_b.trunk_t.1540196593_s.1_v.2_","expires":"2018-10-23T09:23:13.000Z","maxAge":90000,"domain":"messenger.com","path":"/","secure":true,"httpOnly":true,"hostOnly":false,"creation":"2018-10-22T08:23:15.859Z","lastAccessed":"2018-10-22T08:23:17.234Z"},{"key":"presence","value":"EDvF3EtimeF1540196597EuserFA21B27295904383A2EstateFDutF0Et2F_5b_5dElm2FnullEuct2F1540196597047EtrFnullEtwF3725802356EatF1540196597047CEchFDp_5f1B27295904383F0CC","domain":"messenger.com","path":"/","secure":true,"hostOnly":false,"creation":"2018-10-22T08:23:17.047Z","lastAccessed":"2018-10-22T08:23:17.234Z"},{"key":"locale","value":"en_US","domain":"messenger.com","path":"/","secure":true,"hostOnly":false,"creation":"2018-10-22T08:23:17.047Z","lastAccessed":"2018-10-22T08:23:17.234Z"}]